Trees/AVLTree.py
Trees/BST.py
Trees/BinaryTree.py
Trees/Heap.py
cs46_trees-1.0.0.dist-info/LICENSE
cs46_trees-1.0.0.dist-info/METADATA
cs46_trees-1.0.0.dist-info/WHEEL
cs46_trees-1.0.0.dist-info/entry_points.txt
cs46_trees-1.0.0.dist-info/top_level.txt
cs46_trees-1.0.0.dist-info/RECORD
