Metadata-Version: 2.1
Name: cs46-trees
Version: 1.0.0
Summary: Implementing Binary Search Trees, AVLS, and Heaps
Home-page: https://github.com/lindseytam/trees
Author: Lindsey Tam
Author-email: ltaa2018@mymail.pomona.edu
License: GPLv3
Platform: UNKNOWN
Classifier: Programming Language :: Python :: 3
Classifier: Programming Language :: Python :: 3.7
Requires-Dist: pytest
Requires-Dist: hypothesis
